MANIFEST.in
README.md
requirements.txt
setup.py
whois_charman.egg-info/PKG-INFO
whois_charman.egg-info/SOURCES.txt
whois_charman.egg-info/dependency_links.txt
whois_charman.egg-info/entry_points.txt
whois_charman.egg-info/requires.txt
whois_charman.egg-info/top_level.txt
whoischarman/__init__.py
whoischarman/ai/__init__.py
whoischarman/cli/__init__.py
whoischarman/cli/hightlight.min.css
whoischarman/cli/hightlight.min.js
whoischarman/cli/index.html
whoischarman/cli/python.min.js
whoischarman/cli/schedule.py
whoischarman/cli/script-manager.html
whoischarman/cli/test.py
whoischarman/exchangers/__init__.py
whoischarman/exchangers/base.py
whoischarman/exchangers/kalshi.py
whoischarman/exchangers/polymarket.py
whoischarman/stratigy/__init__.py
whoischarman/stratigy/auto_loader.py
whoischarman/stratigy/base_task.py
whoischarman/stratigy/schdule.py
whoischarman/stratigy/scheduler.py
whoischarman/struct/__init__.py
whoischarman/struct/db.py
whoischarman/struct/exchange.py
whoischarman/struct/schedule.py
whoischarman/struct/user.py