Metadata-Version: 2.1
Name: whois-charman
Version: 0.1.3
Summary: A cross-blockchain event prediction exchange arbitrage platform
Home-page: https://git.me/dr/whois-charman
Author: mroy
Author-email: mroy@example.com
Project-URL: Bug Reports, https://git.me/dr/whois-charman/issues
Project-URL: Source, https://git.me/dr/whois-charman
Project-URL: Documentation, https://git.me/dr/whois-charman/docs
Keywords: arbitrage,prediction markets,blockchain,trading,finance,kalshi,polymarket,cryptocurrency,betting,financial analysis
Classifier: Development Status :: 4 - Beta
Classifier: Intended Audience :: Developers
Classifier: Intended Audience :: Financial and Insurance Industry
Classifier: Topic :: Office/Business :: Financial :: Investment
Classifier: Topic :: Software Development :: Libraries :: Python Modules
Classifier: License :: OSI Approved :: MIT License
Classifier: Programming Language :: Python :: 3
Classifier: Programming Language :: Python :: 3.8
Classifier: Programming Language :: Python :: 3.9
Classifier: Programming Language :: Python :: 3.10
Classifier: Programming Language :: Python :: 3.11
Classifier: Programming Language :: Python :: 3.12
Classifier: Operating System :: OS Independent
Requires-Python: >=3.8
Requires-Dist: py-clob-client
Requires-Dist: kalshi-python
Requires-Dist: click>=8.0.0
Requires-Dist: rich>=13.0.0
Requires-Dist: cryptography
Requires-Dist: python-dotenv
Requires-Dist: pyreadline3>=3.4.1
Requires-Dist: tabulate>=0.9.0
Requires-Dist: fastapi>=0.104.0
Requires-Dist: uvicorn>=0.24.0
Requires-Dist: websockets>=12.0
Requires-Dist: pydantic>=2.5.0
Requires-Dist: aiohttp>=3.9.0
Requires-Dist: APScheduler>=3.10.0
Requires-Dist: PyJWT>=2.8.0
Requires-Dist: sqlalchemy>=2.0.0
Requires-Dist: alembic>=1.12.0
Requires-Dist: PyYAML>=6.0.0
Requires-Dist: loguru
Requires-Dist: web3>=6.0.0
Requires-Dist: requests-toolbelt==1.0.0
Requires-Dist: urllib3==2.5.0
Provides-Extra: dev
Requires-Dist: pytest>=7.0.0; extra == "dev"
Requires-Dist: pytest-asyncio>=0.21.0; extra == "dev"
Requires-Dist: black>=23.0.0; extra == "dev"
Requires-Dist: flake8>=6.0.0; extra == "dev"
Requires-Dist: mypy>=1.0.0; extra == "dev"
Provides-Extra: docs
Requires-Dist: sphinx>=5.0.0; extra == "docs"
Requires-Dist: sphinx-rtd-theme>=1.0.0; extra == "docs"
